README.md
setup.cfg
setup.py
nomad_envoy_utils_cli/__init__.py
nomad_envoy_utils_cli/api_client.py
nomad_envoy_utils_cli/configuration.py
nomad_envoy_utils_cli/exceptions.py
nomad_envoy_utils_cli/rest.py
nomad_envoy_utils_cli.egg-info/PKG-INFO
nomad_envoy_utils_cli.egg-info/SOURCES.txt
nomad_envoy_utils_cli.egg-info/dependency_links.txt
nomad_envoy_utils_cli.egg-info/requires.txt
nomad_envoy_utils_cli.egg-info/top_level.txt
nomad_envoy_utils_cli/api/__init__.py
nomad_envoy_utils_cli/api/health_api.py
nomad_envoy_utils_cli/api/platform_api.py
nomad_envoy_utils_cli/models/__init__.py
nomad_envoy_utils_cli/models/api_response.py
nomad_envoy_utils_cli/models/api_response_data.py
nomad_envoy_utils_cli/models/cypher.py
nomad_envoy_utils_cli/models/cypher_operation.py
test/test_api_response.py
test/test_api_response_data.py
test/test_cypher.py
test/test_cypher_operation.py
test/test_health_api.py
test/test_platform_api.py