Metadata-Version: 2.1
Name: nomad-envoy-utils-cli
Version: 1.3.0
Summary: Nomad Envoy Utils
Home-page: UNKNOWN
Author: OpenAPI Generator community
Author-email: paul@samarkand.global
License: UNKNOWN
Keywords: OpenAPI,OpenAPI-Generator,Nomad Envoy Utils
Platform: UNKNOWN
